{
  "id": "rss-20260721-011",
  "title": "Deterministic Replay for AI Agent Systems",
  "source": "rss:arXiv cs.AI",
  "source_url": "https://arxiv.org/abs/2607.16200",
  "author": "arXiv cs.AI",
  "published_at": "2026-07-21T10:31:16.685178+00:00",
  "collected_at": "2026-07-21T10:31:16.685178+00:00",
  "summary": "本文提出了一种针对AI Agent系统的确定性重放方法，旨在解决Agent行为不可复现的问题。通过记录和重放关键状态，该方法能提升调试和测试的可靠性，对构建稳健的Agent系统具有实用价值。",
  "score": 7,
  "tags": [
    "agent",
    "evaluation"
  ],
  "audience": "intermediate",
  "status": "review",
  "updated_at": "2026-07-21T10:32:20.380617+00:00"
}